{
  "updated_at": "2026-04-14T15:02:33.017Z",
  "dry_run": false,
  "results": {
    "be": {
      "before": 11837,
      "after": 11837,
      "added": 0
    },
    "nl": {
      "before": 20055,
      "after": 20055,
      "added": 0
    },
    "de": {
      "before": 6959,
      "after": 6959,
      "added": 0
    },
    "gb": {
      "before": 32094,
      "after": 32094,
      "added": 0
    },
    "us": {
      "before": 18363,
      "after": 18374,
      "added": 11
    },
    "ca": {
      "before": 10969,
      "after": 10969,
      "added": 0
    },
    "fr": {
      "before": 3895,
      "after": 3895,
      "added": 0
    },
    "it": {
      "before": 8795,
      "after": 8806,
      "added": 11
    }
  }
}